[{"Id":1,"Dataset":"Asset Table","Dataset Type":"Base","Property":"Id","Property Type":"Int"},{"Id":18,"Dataset":"Property Table","Dataset Type":"Base","Property":"Id","Property Type":"Int"},{"Id":23,"Dataset":"Location Table","Dataset Type":"Base","Property":"Id","Property Type":"Int"},{"Id":31,"Dataset":"Road Table","Dataset Type":"Base","Property":"Id","Property Type":"Int"},{"Id":41,"Dataset":"Cycle Table","Dataset Type":"Discrete","Property":"Id","Property Type":"Int"},{"Id":70,"Dataset":"Position Table","Dataset Type":"Discrete","Property":"Id","Property Type":"Int"},{"Id":87,"Dataset":"Oil Table","Dataset Type":"Discrete","Property":"Id","Property Type":"Int"},{"Id":146,"Dataset":"Fuel Table","Dataset Type":"Discrete","Property":"Id","Property Type":"Int"},{"Id":163,"Dataset":"Counter Table","Dataset Type":"Discrete","Property":"Id","Property Type":"Int"},{"Id":181,"Dataset":"Sensor Table","Dataset Type":"Discrete","Property":"Id","Property Type":"Int"},{"Id":198,"Dataset":"Sensor Table","Dataset Type":"Discrete","Property":"Occurences","Property Type":"Int"},{"Id":201,"Dataset":"Time Table","Dataset Type":"Interval","Property":"Id","Property Type":"Int"},{"Id":229,"Dataset":"Activity Table","Dataset Type":"Interval","Property":"Id","Property Type":"Int"},{"Id":249,"Dataset":"Excavator Activity Table","Dataset Type":"Interval","Property":"Id","Property Type":"Int"},{"Id":268,"Dataset":"Roster Table","Dataset Type":"Interval","Property":"Id","Property Type":"Int"},{"Id":276,"Dataset":"Login Table","Dataset Type":"Interval","Property":"Id","Property Type":"Int"}]